pyglm/glm_typing.py
pyglm/glm.cpython-310-x86_64-linux-gnu.so
pyglm/__init__.py
pyglm/__init__.pyi
glm/py.typed
glm/__init__.py
pyglm-stubs/LICENSE
pyglm-stubs/__init__.py
pyglm-stubs/glm/__init__.py
pyglm-stubs/glm/__init__.pyi
pyglm-2.8.1.dist-info/WHEEL
pyglm-2.8.1.dist-info/RECORD
pyglm-2.8.1.dist-info/top_level.txt
pyglm-2.8.1.dist-info/METADATA
pyglm-2.8.1.dist-info/licenses/LICENSE
pyglm-2.8.1.dist-info/licenses/COPYING
