Metadata-Version: 2.4
Name: pyglm
Version: 2.8.1
Summary: OpenGL Mathematics library for Python
Author: Zuzu_Typ
Author-email: zuzu.typ@gmail.com
License: Zlib
Project-URL: Source Code, https://github.com/Zuzu-Typ/PyGLM/
Project-URL: Documentation, https://github.com/Zuzu-Typ/PyGLM/wiki
Keywords: GLM,OpenGL,matrix,vector,vec,mat,Mathematics,3D,python,python3,3,library,python-c-api,c-api,math-library,numpy,pyrr,pip,pypi,matrix-manipulation,matrix-multiplication,matrix-functions,quaternion,c,glsl
Classifier: Development Status :: 5 - Production/Stable
Classifier: Intended Audience :: Developers
Classifier: License :: OSI Approved :: zlib/libpng License
Classifier: Programming Language :: Python :: 3 :: Only
Classifier: Programming Language :: Python :: 3
Classifier: Programming Language :: Python :: 3.9
Classifier: Programming Language :: Python :: 3.10
Classifier: Programming Language :: Python :: 3.11
Classifier: Programming Language :: Python :: 3.12
Classifier: Programming Language :: Python :: 3.13
Classifier: Operating System :: Microsoft :: Windows
Classifier: Operating System :: POSIX :: Linux
Classifier: Operating System :: MacOS
Classifier: Topic :: Multimedia :: Graphics
Classifier: Topic :: Software Development :: Libraries
Classifier: Topic :: Scientific/Engineering :: Physics
Classifier: Typing :: Typed
License-File: LICENSE
License-File: COPYING
Dynamic: license-file
